batch_convert.py
minimal_template.py
mod_parser.py
xm2live.py
xm_parser.py
xm2live-3.0.0.dist-info/licenses/LICENSE
xm2live-3.0.0.dist-info/METADATA
xm2live-3.0.0.dist-info/WHEEL
xm2live-3.0.0.dist-info/entry_points.txt
xm2live-3.0.0.dist-info/top_level.txt
xm2live-3.0.0.dist-info/RECORD
