Metadata-Version: 2.4
Name: xm2live
Version: 3.0.0
Summary: Convert FastTracker 2 XM and Amiga ProTracker MOD files to Ableton Live projects
Author: Sam Kieffer
License-Expression: MIT
Project-URL: Homepage, https://github.com/samkieffer/xm2live
Project-URL: Repository, https://github.com/samkieffer/xm2live
Project-URL: Issues, https://github.com/samkieffer/xm2live/issues
Keywords: tracker,fasttracker,protracker,xm,mod,ableton,live,converter,music,demoscene
Classifier: Development Status :: 5 - Production/Stable
Classifier: Environment :: Console
Classifier: Intended Audience :: End Users/Desktop
Classifier: Operating System :: OS Independent
Classifier: Programming Language :: Python :: 3
Classifier: Programming Language :: Python :: 3.8
Classifier: Programming Language :: Python :: 3.9
Classifier: Programming Language :: Python :: 3.10
Classifier: Programming Language :: Python :: 3.11
Classifier: Programming Language :: Python :: 3.12
Classifier: Topic :: Multimedia :: Sound/Audio :: Conversion
Classifier: Topic :: Multimedia :: Sound/Audio :: MIDI
Requires-Python: >=3.8
License-File: LICENSE
Requires-Dist: buildable>=0.1.0
Requires-Dist: numpy>=1.20.0
Requires-Dist: lxml>=4.6.0
Dynamic: license-file
